medis/CDI.py
medis/MKIDS.py
medis/__init__.py
medis/aberrations.py
medis/adaptive.py
medis/atmosphere.py
medis/coronagraphy.py
medis/distribution.py
medis/medis_main.py
medis/optics.py
medis/params.py
medis/plot_tools.py
medis/telescope.py
medis/twilight_colormaps.py
medis/utils.py
simulations/__init__.py
simulations/check_sampling.py
simulations/Subaru/SCExAO_DM.py
simulations/Subaru/Subaru_SCExAO.py
simulations/Subaru/Subaru_frontend.py
simulations/Subaru/__init__.py
simulations/Subaru/run_SCExAO-DM.py
simulations/Subaru/run_SCExAO.py
simulations/Subaru/run_SubaruFrontend.py
simulations/examples/Hubble_frontend.py
simulations/examples/__init__.py
simulations/general_telescope/__init__.py
simulations/general_telescope/general_telescope.py
simulations/general_telescope/run_general.py
medis-0.0.2.dist-info/LICENSE
medis-0.0.2.dist-info/METADATA
medis-0.0.2.dist-info/WHEEL
medis-0.0.2.dist-info/top_level.txt
medis-0.0.2.dist-info/RECORD
