Metadata-Version: 2.1
Name: medis
Version: 0.0.2
Summary: MKID Exoplanet Direct Imaging Simulator
Home-page: https://github.com/MazinLab/MEDIS
Author: R. Dodkins, K. Davis
Author-email: dodkins@ucsb.edu
License: UNKNOWN
Platform: UNKNOWN
